chronowatch/__init__.py
chronowatch/stopwatch.py
chronowatch-1.0.0.dist-info/LICENSE
chronowatch-1.0.0.dist-info/METADATA
chronowatch-1.0.0.dist-info/WHEEL
chronowatch-1.0.0.dist-info/top_level.txt
chronowatch-1.0.0.dist-info/RECORD
