Metadata-Version: 2.1
Name: chronowatch
Version: 1.0.0
Summary: A simple stopwatch for measuring code performance
Home-page: https://github.com/Ahmad-Said/chrono_stopwatch
Author: Ahmad SAID
Author-email: hunter.sc.dark@gmail.com
License: MIT
Keywords: stopwatch,profile
Classifier: Development Status :: 4 - Beta
Classifier: Intended Audience :: Developers
Classifier: License :: OSI Approved :: MIT License
Classifier: Programming Language :: Python :: 3
Classifier: Programming Language :: Python :: 3 :: Only
Requires-Python: >=3.7
License-File: LICENSE
Requires-Dist: python-tml
Requires-Dist: typing-extensions
